README.md
setup.py
seispro/__init__.py
seispro/agc.py
seispro/fxdecon.py
seispro/shared.py
seispro/tfclip.py
seispro.egg-info/PKG-INFO
seispro.egg-info/SOURCES.txt
seispro.egg-info/dependency_links.txt
seispro.egg-info/requires.txt
seispro.egg-info/top_level.txt